Workbook

Sheet Start Here
A1: 30-Day AI Automation Advanced Sprint
A2: An architecture-and-governance program for durable orchestration, agent platforms, Voice AI at scale, security and executive production readiness.
A4: PROGRAM SETUP | D4: COMPLETED DAYS | F4: OVERALL PROGRESS
A5: Recommended pace | C5: 3 | D5: =COUNTIF('30-Day Plan'!$K$5:$K$34,"Completed") -> 0 | F5: =COUNTIF('30-Day Plan'!$K$5:$K$34,"Completed")/COUNTA('30-Day Plan'!$A$5:$A$34) -> 0
A6: Start date | D6: PLANNED HOURS | F6: AVERAGE QUIZ SCORE
A7: Target role | C7: AI Systems Architect & Automation Lead | D7: =SUM('30-Day Plan'!$J$5:$J$34) -> 90 | F7: =IFERROR(AVERAGE('30-Day Plan'!$L$5:$L$34)/100,0) -> 0
A9: THE FIVE-BLOCK ROADMAP
A10: 01 PLATFORM ARCHITECTURE | C10: Days 1-7 | D10: Events, contracts, durable state, resilience and delivery | Milestone: platform architecture
A11: 02 AGENT PLATFORMS | C11: Days 8-15 | D11: Orchestration, model policy, governed RAG, evals and tracing
A12: 03 VOICE AT SCALE | C12: Days 16-20 | D12: Carrier/SIP resilience, latency, capacity and compliant outbound control
A13: 04 GOVERNANCE & OPS | C13: Days 21-26 | D13: Enterprise sync, experiments, threat models, incidents and audit evidence
A14: 05 EXECUTIVE CAPSTONE | C14: Days 27-30 | D14: Reference architecture, production review, executive case and defense
A16: DAILY OPERATING RHYTHM | 3 HOURS
A17: LEARN | 60 MIN | D17: BUILD | 90 MIN | G17: TEST | 30 MIN
A18: Study one focused concept. Take concise notes and explain the idea in your own words. | D18: Implement the day's workflow with synthetic data. Make the happy path work end to end. | G18: Test failures and edge cases, then save evidence before marking the day complete.
A21: DEFINITION OF DONE | MARK A DAY COMPLETE ONLY WHEN ALL FIVE ARE TRUE
A22: 1. The daily deliverable exists and can be opened, demonstrated or inspected.
A23: 2. The main success path works with synthetic test data.
A24: 3. At least one failure or edge case has been tested and documented.
A25: 4. Evidence is saved in the Notes / Evidence Link cell for that day.
A26: 5. You can explain what you built, why it matters and what you would improve next.
A28: EDITING GUIDE | Yellow cells are your inputs. Blue values calculate automatically. Green means complete; red means blocked or unresolved.

Sheet 30-Day Plan
A1: 30-Day Advanced Learning Plan
A2: Assumes production build experience. Daily rhythm: architecture study (45 min) -> implementation/design (105 min) -> evidence and review (30 min).
A4: Day | B4: Planned Date | C4: Phase | D4: Main Focus | E4: Learning Outcome | F4: Study / Learn | G4: Hands-On Build | H4: Daily Deliverable | I4: Primary Tools | J4: Hours | K4: Status | L4: Quiz % | M4: Notes / Evidence Link
A5: 1 | B5: =IF('Start Here'!$C$6="","",'Start Here'!$C$6+A5-1) | C5: Block 1 | Platform Architecture | D5: Enterprise discovery and portfolio strategy | E5: Translate company goals, constraints and risk appetite into an automation portfolio. | F5: Study capability maps, operating models, value streams, governance and portfolio prioritization. | G5: Create a Medicare agency capability map and prioritize systems by value, dependency and regulatory risk. | H5: Executive automation portfolio with sequencing rationale. | I5: Architecture canvas | J5: 3 | K5: Not Started
A6: 2 | B6: =IF('Start Here'!$C$6="","",'Start Here'!$C$6+A6-1) | C6: Block 1 | Platform Architecture | D6: Event-driven architecture and queues | E6: Design systems that absorb bursts, isolate failures and process events asynchronously. | F6: Study producers/consumers, queues, topics, ordering, delivery semantics and backpressure. | G6: Design lead, call, appointment and consent events with queue-based processing and retry paths. | H6: Event catalog and sequence diagrams. | I6: n8n + queue concepts | J6: 3 | K6: Not Started
A7: 3 | B7: =IF('Start Here'!$C$6="","",'Start Here'!$C$6+A7-1) | C7: Block 1 | Platform Architecture | D7: Enterprise data contracts | E7: Govern identifiers, schemas and ownership across CRM, telephony, AI and analytics. | F7: Study schema evolution, canonical models, lineage, PII classification and contract testing. | G7: Define versioned contracts for customer, consent, call, appointment, task and outcome events. | H7: Versioned schema pack and ownership matrix. | I7: JSON Schema + API specs | J7: 3 | K7: Not Started
A8: 4 | B8: =IF('Start Here'!$C$6="","",'Start Here'!$C$6+A8-1) | C8: Block 1 | Platform Architecture | D8: Durable orchestration and replay | E8: Preserve long-running workflow state and recover deterministically after interruptions. | F8: Study workflow state, checkpoints, retries, compensation, replay and exactly-once business effects. | G8: Design an enrollment-adjacent appointment workflow that can pause, approve, resume and compensate. | H8: Durable orchestration design and replay test plan. | I8: Workflow engine + n8n | J8: 3 | K8: Not Started
A9: 5 | B9: =IF('Start Here'!$C$6="","",'Start Here'!$C$6+A9-1) | C9: Block 1 | Platform Architecture | D9: API resilience and backpressure | E9: Protect downstream systems while meeting business SLAs under failure and load. | F9: Study circuit breakers, concurrency limits, bulkheads, rate limits, jitter, timeouts and fallback. | G9: Build a load-safe integration path with bounded concurrency, adaptive retry and failure isolation. | H9: Resilience test results and capacity assumptions. | I9: n8n + API gateway | J9: 3 | K9: Not Started
A10: 6 | B10: =IF('Start Here'!$C$6="","",'Start Here'!$C$6+A10-1) | C10: Block 1 | Platform Architecture | D10: Environment promotion and secrets | E10: Move changes from development to production with traceability and rollback. | F10: Study environment separation, secret rotation, change approval, CI checks and release artifacts. | G10: Create a promotion pipeline for workflows, prompts, schemas, evals and configuration. | H10: Release pipeline design and rollback package. | I10: Git + CI/CD | J10: 3 | K10: Not Started
A11: 7 | B11: =IF('Start Here'!$C$6="","",'Start Here'!$C$6+A11-1) | C11: Block 1 | Platform Architecture | D11: Architecture review milestone | E11: Defend a complete platform design against reliability, security, cost and operational concerns. | F11: Review Days 1-6 and write explicit architecture decisions and rejected alternatives. | G11: Produce a reference architecture for the agency automation platform and conduct a design review. | H11: Portfolio Project 1 architecture, ADRs and review findings. | I11: Architecture tools | J11: 3 | K11: Not Started
A12: 8 | B12: =IF('Start Here'!$C$6="","",'Start Here'!$C$6+A12-1) | C12: Block 2 | Agent Platforms | D12: Agent planning and execution boundaries | E12: Separate reasoning, policy, tool execution and deterministic business controls. | F12: Study planner/executor patterns, state, permissions, tool isolation and deterministic validators. | G12: Design an agent runtime where models propose actions and trusted services validate/execute them. | H12: Agent runtime sequence and trust-boundary diagram. | I12: OpenAI + service layer | J12: 3 | K12: Not Started
A13: 9 | B13: =IF('Start Here'!$C$6="","",'Start Here'!$C$6+A13-1) | C13: Block 2 | Agent Platforms | D13: Multi-agent routing and delegation | E13: Use specialization only where it improves control, evaluation or maintainability. | F13: Study routing, delegation, shared context, handoff contracts and termination conditions. | G13: Build a dispatcher for receptionist, service, scheduling and compliance-review agents. | H13: Routing policy and cross-agent test suite. | I13: Agents SDK / Vapi squads | J13: 3 | K13: Not Started
A14: 10 | B14: =IF('Start Here'!$C$6="","",'Start Here'!$C$6+A14-1) | C14: Block 2 | Agent Platforms | D14: Model routing, fallback and cost | E14: Match models to tasks while preserving quality during outages or performance changes. | F14: Study capability tiers, latency, reasoning effort, fallback chains, caching and cost budgets. | G14: Create a policy for classification, retrieval, summarization, complex reasoning and voice tasks. | H14: Model-routing matrix with quality/cost tests. | I14: OpenAI + gateway | J14: 3 | K14: Not Started
A15: 11 | B15: =IF('Start Here'!$C$6="","",'Start Here'!$C$6+A15-1) | C15: Block 2 | Agent Platforms | D15: Permission-aware RAG | E15: Enforce document access, freshness and provenance during retrieval and generation. | F15: Study ACL filtering, tenant boundaries, hybrid retrieval, reranking, lineage and deletion propagation. | G15: Design and test a knowledge service that filters sources by role, purpose and effective date. | H15: Permission tests and retrieval quality report. | I15: Vector DB + OpenAI | J15: 3 | K15: Not Started
A16: 12 | B16: =IF('Start Here'!$C$6="","",'Start Here'!$C$6+A16-1) | C16: Block 2 | Agent Platforms | D16: Evaluation and red-team milestone | E16: Create release gates that measure task success, policy compliance and tool behavior. | F16: Study golden datasets, trajectory evaluation, LLM judges, adversarial testing and statistical confidence. | G16: Build 100 cases across service, scheduling, privacy, prompt injection and tool misuse. | H16: Portfolio Project 2 eval suite and release thresholds. | I16: OpenAI Evals | J16: 3 | K16: Not Started
... A34: 30 | B34: =IF('Start Here'!$C$6="","",'Start Here'!$C$6+A34-1) | C34: Block 5 | Executive Capstone | D34: Architecture defense | E34: Defend the design against CTO, operations, compliance and finance questions. | F34: Review tradeoffs, rejected options, residual risk, cost, staffing and success measures. | G34: Run a 75-minute architecture board simulation and revise unsupported decisions. | H34: Final architect readiness score and 90-day growth plan. | I34: Review board + workbook | J34: 3 | K34: Not Started

Sheet Portfolio Projects
A1: Portfolio Projects
A2: Use synthetic data. A portfolio project is complete only when it has a demo, architecture, tests, failure handling and a clear business result.
A4: Project | B4: Business Problem | C4: Core Workflow | D4: Required Controls | E4: Proof / Deliverables | F4: Success Metrics | G4: Target Day | H4: Status
A5: 1. Event-Driven Automation Platform | B5: Growth is constrained by synchronous, tightly coupled automations. | C5: Domain events -> queues -> durable workflows -> services -> reconciliation and analytics. | D5: Versioned contracts, backpressure, replay, compensation, isolation and environment promotion. | E5: Reference architecture, ADRs, schemas, load tests and review report. | F5: Peak load absorbed; replay is safe; dependencies and failure domains are explicit. | G5: 7 | H5: Not Started
A6: 2. Governed Agent Platform | B6: Teams deploy agents without consistent permissions, evaluation or release controls. | C6: Request -> router -> model/retrieval/tools -> validators/approvals -> trace/evaluation. | D6: Risk tiers, model policy, permission-aware RAG, red team, release gates and rollback. | E6: 100-case eval, trace view, governance pack and platform demo. | F6: Release thresholds met; high-risk actions are independently controlled and evidenced. | G6: 12 | H6: Not Started
A7: 3. Voice AI at Scale | B7: Single-agent voice systems lack capacity, carrier resilience and measurable quality. | C7: Carrier/SIP -> routing -> voice agents -> tools -> transfer pools -> monitoring/failover. | D7: CPS/concurrency limits, secure trunking, latency SLOs, suppression and disaster recovery. | E7: 100-call simulation, concurrency test, failover test and capacity plan. | F7: SLOs met under target load; failover works; compliance-negative tests block calls. | G7: 20 | H7: Not Started
A8: 4. Medicare Automation Reference Architecture | B8: Automation investments lack a unified business, technical and control architecture. | C8: Channels -> policy/identity -> agent/workflow platform -> CRM/data -> analytics/governance. | D8: SLOs, control evidence, threat model, incident response, cost model and operating ownership. | E8: Executive brief, technical pack, roadmap, PRR and 10-minute demo. | F8: Architecture passes technical, operational, security and compliance review. | G8: 29 | H8: Not Started

Sheet Skills Tracker
A1: Skills Readiness Tracker
A2: Score yourself honestly from 1–5. A target-level score requires evidence: a working build, test result, architecture explanation or documented operating procedure.
A4: Category | B4: Skill | C4: Target Level | D4: Current Level | E4: Gap | F4: Evidence Required | G4: Best Practice Days | H4: Evidence / Link
A5: Strategy | B5: Enterprise discovery and portfolio design | C5: 5 | D5: 3 | E5: =MAX(0,C5-D5) -> 2 | F5: Capability map + sequenced portfolio | G5: 1
A6: Architecture | B6: Events, queues and bounded contexts | C6: 5 | D6: 3 | E6: =MAX(0,C6-D6) -> 2 | F6: Event catalog + reference architecture | G6: 2, 7
A7: Data | B7: Versioned contracts and lineage | C7: 5 | D7: 3 | E7: =MAX(0,C7-D7) -> 2 | F7: Schema pack + ownership matrix | G7: 3
A8: Orchestration | B8: Durable state, replay and compensation | C8: 5 | D8: 3 | E8: =MAX(0,C8-D8) -> 2 | F8: Replay-safe workflow design | G8: 4
A9: Reliability | B9: Backpressure, SLOs and failover | C9: 5 | D9: 3 | E9: =MAX(0,C9-D9) -> 2 | F9: Load/failover evidence | G9: 5, 18, 28
A10: Delivery | B10: CI/CD, environments and secrets | C10: 4 | D10: 3 | E10: =MAX(0,C10-D10) -> 1 | F10: Promotion and rollback design | G10: 6
A11: Agents | B11: Orchestration and model routing | C11: 5 | D11: 3 | E11: =MAX(0,C11-D11) -> 2 | F11: Agent runtime + model policy | G11: 8-10
A12: Knowledge | B12: Permission-aware RAG governance | C12: 5 | D12: 3 | E12: =MAX(0,C12-D12) -> 2 | F12: ACL retrieval tests | G12: 11
A13: Quality | B13: Evals, red teaming and release gates | C13: 5 | D13: 3 | E13: =MAX(0,C13-D13) -> 2 | F13: 100-case eval and gate | G13: 12, 15
A14: Observability | B14: Distributed tracing and incidents | C14: 5 | D14: 3 | E14: =MAX(0,C14-D14) -> 2 | F14: Trace view + incident analysis | G14: 13, 25
A15: Voice | B15: SIP, capacity and latency engineering | C15: 5 | D15: 3 | E15: =MAX(0,C15-D15) -> 2 | F15: 100-call scale scorecard | G15: 16-20
A16: Security | B16: Threat modeling and data governance | C16: 5 | D16: 3 | E16: =MAX(0,C16-D16) -> 2 | F16: Threat model + remediation | G16: 24
... A18: Leadership | B18: Executive narrative and architecture defense | C18: 5 | D18: 3 | E18: =MAX(0,C18-D18) -> 2 | F18: Executive pack + review board | G18: 27-30

Sheet Compliance
A1: Medicare & Healthcare Automation Checkpoints
A2: Training checklist—not legal advice. Confirm current federal/state requirements, carrier rules and agency counsel before deployment. Use synthetic data during learning.
A4: Area | B4: Question Before Launch | C4: Expected Control | D4: Evidence | E4: Owner | F4: Status | G4: Official Source
A5: AI voice / TCPA | B5: Is this outbound call using an artificial or prerecorded voice, and is the required consent documented? | C5: Eligibility gate before dialing; timestamped consent evidence; caller identification and opt-out path. | D5: Consent record + dial decision log | E5: Compliance | F5: Not Reviewed | G5: https://docs.fcc.gov/public/attachments/FCC-24-17A1_Rcd.pdf
A6: Do Not Call | B6: Are National, state and entity-specific DNC/STOP requests suppressed? | C6: Central suppression list checked before contact; immediate STOP/DNC update across channels. | D6: Suppression test + audit log | E6: Compliance | F6: Not Reviewed | G6: https://www.ftc.gov/business-guidance/resources/complying-telemarketing-sales-rule
A7: Medicare contact | B7: Did the beneficiary initiate contact or provide permission for the specific follow-up? | C7: No unsolicited Medicare cold-calling; store source, purpose, seller and permission evidence. | D7: Lead provenance + permission record | E7: Licensed lead | F7: Not Reviewed | G7: https://www.cms.gov/medicare/health-drug-plans/managed-care-marketing/medicare-guidelines
A8: TPMO data sharing | B8: If beneficiary data is shared with another TPMO, is one-to-one written consent present? | C8: Separate transparent consent per recipient TPMO; block transfer if missing. | D8: Consent text, timestamp and recipient | E8: Compliance | F8: Not Reviewed | G8: https://www.cms.gov/newsroom/fact-sheets/contract-year-2025-medicare-advantage-part-d-final-rule-cms-4205-f
A9: Call recording | B9: Must this marketing, sales or enrollment call be recorded and retained? | C9: Record the complete required call, protect access and follow approved retention policy. | D9: Recording ID + retention metadata | E9: Compliance/IT | F9: Not Reviewed | G9: https://www.cms.gov/files/document/cy2026agentbrokertrainingtestingguidelinespdf.pdf
A10: Licensed activity | B10: Could the AI be interpreting benefits, recommending a plan or enrolling someone? | C10: Restrict AI to approved administrative tasks; transfer regulated advice and enrollment to an appropriately licensed agent. | D10: Prompt rule + transfer tests | E10: Licensed agent | F10: Not Reviewed | G10: https://www.cms.gov/medicare/health-drug-plans/managed-care-marketing/medicare-marketing-guidelines/agent-broker-compensation
A11: PHI / HIPAA | B11: Will any vendor create, receive, maintain or transmit ePHI for a covered entity/business associate? | C11: Confirm regulatory role, BAA, permitted use, risk analysis, access, encryption, retention and incident process. | D11: Vendor approval + BAA + data flow | E11: Privacy/Security | F11: Not Reviewed | G11: https://www.hhs.gov/hipaa/for-professionals/special-topics/health-information-technology/cloud-computing/index.html
A12: Data minimization | B12: Does the workflow collect only what it needs for the approved purpose? | C12: Remove unnecessary fields from prompts, transcripts, logs and notifications; mask sensitive values. | D12: Field inventory + minimization review | E12: System owner | F12: Not Reviewed | G12: https://www.hhs.gov/hipaa/for-professionals/privacy/index.html
A13: Human escalation | B13: Can the AI recognize uncertainty, complaints, emergencies and explicit requests for a human? | C13: Defined transfer triggers, safe fallback, after-hours route and failed-transfer alert. | D13: Scenario tests + routing table | E13: Operations | F13: Not Reviewed | G13: https://elevenlabs.io/docs/eleven-agents/customization/tools/system-tools/transfer-to-number
A14: Audit & incidents | B14: Can the team reconstruct what happened and respond to an error? | C14: Log consent decision, model/tool result, record changes, owner, error and recovery without exposing excess sensitive data. | D14: Audit sample + incident runbook | E14: IT/Operations | F14: Not Reviewed | G14: https://www.hhs.gov/hipaa/for-professionals/security/laws-regulations/index.html

Sheet Interview Prep
A1: Interview Preparation
A2: Answer in this order: business problem → architecture → controls/failure paths → human handoff → metrics. Use evidence from your portfolio; never invent client outcomes.
A4: # | B4: Interview Question | C4: A Strong Answer Must Include | D4: Your Answer Notes | E4: Evidence / Project | F4: Confidence (1–5)
A5: 1 | B5: How would you architect an enterprise automation platform for this agency? | C5: Capabilities, domains, events, orchestration, data, agents, channels, controls, SLOs, ownership and roadmap. | F5: 3
A6: 2 | B6: When do queues improve a workflow, and what complexity do they add? | C6: Burst absorption and isolation versus ordering, duplicates, visibility, replay, operations and latency. | F6: 3
A7: 3 | B7: How do you achieve exactly-once business effects? | C7: At-least-once delivery plus idempotency, unique business keys, transaction boundaries and reconciliation. | F7: 3
A8: 4 | B8: How do you evolve data contracts without breaking consumers? | C8: Versioning, compatibility, ownership, contract tests, deprecation and lineage. | F8: 3
A9: 5 | B9: How do you route models across tasks? | C9: Capability/latency/cost tiers, risk, fallback, pinned versions, eval gates and budget telemetry. | F9: 3
A10: 6 | B10: When is multi-agent architecture justified? | C10: Clear specialization, isolation or evaluation benefit; bounded handoffs, shared-state policy and termination. | F10: 3
A11: 7 | B11: How do you enforce permissions in RAG? | C11: Identity and purpose at query time, ACL/tenant filters, provenance, cache isolation and deletion propagation. | F11: 3
A12: 8 | B12: What should an AI release gate measure? | C12: Task success, trajectory/tool correctness, policy, adversarial cases, latency, cost and statistical confidence. | F12: 3
A13: 9 | B13: How do you trace an AI-driven business action? | C13: Correlation across channel, model, retrieval, tool, workflow and CRM while minimizing sensitive logs. | F13: 3
A14: 10 | B14: How would you capacity-plan a voice AI system? | C14: Traffic forecast, CPS/concurrency, latency, tool limits, transfer staffing, overload behavior and failover. | F14: 3
A15: 11 | B15: How do you design voice disaster recovery? | C15: Carrier/SIP diversity, regional paths, DR URLs, health checks, degraded mode, RTO/RPO and exercises. | F15: 3
A16: 12 | B16: How do you threat-model an AI automation platform? | C16: Assets, trust boundaries, prompt/tool/API/vendor threats, likelihood/impact, mitigations and verification. | F16: 3
... A19: 15 | B19: How do you explain build-versus-buy to an executive? | C19: Strategic differentiation, time, control, compliance, integration, total cost, lock-in and staged decision. | F19: 3

Sheet Resources
A1: Official Learning Resources
A2: Start with official documentation. Product features and legal requirements change; verify current instructions before production use.
A4: Topic | B4: Resource | C4: Why It Matters | D4: Use On Day | E4: URL
A5: OpenAI | B5: API compatibility and request IDs | C5: Pinned versions, request tracing and production diagnostics. | D5: 5, 10, 13 | E5: https://platform.openai.com/docs/api-reference/backward-compatibility
A6: OpenAI | B6: Evals API | C6: Programmatic evaluation runs and release evidence. | D6: 12, 15 | E6: https://platform.openai.com/docs/api-reference/evals
A7: OpenAI | B7: Realtime API | C7: Realtime voice sessions, tools, SIP and tracing. | D7: 16-20 | E7: https://platform.openai.com/docs/api-reference/realtime
A8: OpenAI | B8: Data controls | C8: Retention, residency and endpoint data behavior. | D8: 11, 24, 26 | E8: https://platform.openai.com/docs/models/default-usage-policies-by-endpoint
A9: n8n | B9: Queue mode | C9: Worker-based scaling and queue architecture. | D9: 2, 5, 18 | E9: https://docs.n8n.io/hosting/scaling/queue-mode/
A10: n8n | B10: Sub-workflows | C10: Bounded workflow services and reusable contracts. | D10: 4 | E10: https://docs.n8n.io/flow-logic/subworkflows/
A11: Vapi | B11: Simulations | C11: Advanced voice-agent simulation and CI-style testing. | D11: 12, 20 | E11: https://docs.vapi.ai/observability/simulations-quickstart
A12: Vapi | B12: Monitoring | C12: Automated quality monitoring across production calls. | D12: 13, 20 | E12: https://docs.vapi.ai/observability/monitoring-quickstart
A13: Retell AI | B13: Testing overview | C13: Batch simulation and production validation. | D13: 12, 20 | E13: https://docs.retellai.com/test/test-overview
A14: Twilio | B14: Elastic SIP Trunking | C14: Secure trunking, scale, call transfer and disaster recovery. | D14: 16-20 | E14: https://www.twilio.com/docs/sip-trunking
A15: Twilio | B15: Voice failover best practices | C15: Regional routing and failure recovery. | D15: 20, 25 | E15: https://www.twilio.com/docs/voice/twilio-voice-failover-best-practices
... A20: HHS | B20: HIPAA and cloud computing | C20: Business associate, BAA and cloud risk requirements. | D20: 24-26 | E20: https://www.hhs.gov/hipaa/for-professionals/special-topics/health-information-technology/cloud-computing/index.html
